rtml/__init__.py
rtml/config.py
rtml/feature_store_api/__init__.py
rtml/feature_store_api/api.py
rtml/feature_store_api/demo.py
rtml/feature_store_api/types.py
rtml/kraken_api/__init__.py
rtml/kraken_api/historical.py
rtml/kraken_api/types.py
rtml/kraken_api/websocket.py
rtml/logging.py
rtml/ml/predict.py
rtml/ml/preprocessing.py
rtml/ml/train.py
rtml/quix_api/app_factory.py
rtml/quix_api/producer_wrapper.py
rtml-0.1.0.dist-info/METADATA
rtml-0.1.0.dist-info/WHEEL
rtml-0.1.0.dist-info/RECORD
